jacinle/__init__.py
jacinle/logging.py
jacinle/cli/__init__.py
jacinle/cli/argument.py
jacinle/cli/device.py
jacinle/cli/git.py
jacinle/cli/keyboard.py
jacinle/comm/__init__.py
jacinle/comm/broadcast.py
jacinle/comm/cs.py
jacinle/comm/cs_simple.py
jacinle/comm/echo.py
jacinle/comm/gather.py
jacinle/comm/service.py
jacinle/comm/service_name_server.py
jacinle/comm/distrib/__init__.py
jacinle/comm/distrib/_configs.py
jacinle/comm/distrib/controller.py
jacinle/comm/distrib/name_server.py
jacinle/comm/distrib/pipe.py
jacinle/concurrency/__init__.py
jacinle/concurrency/counter.py
jacinle/concurrency/event.py
jacinle/concurrency/future.py
jacinle/concurrency/packing.py
jacinle/concurrency/pool.py
jacinle/concurrency/process.py
jacinle/concurrency/queue.py
jacinle/concurrency/shmarray.py
jacinle/concurrency/zmq_utils.py
jacinle/config/__init__.py
jacinle/config/environ.py
jacinle/config/environ_v2.py
jacinle/config/g.py
jacinle/image/__init__.py
jacinle/image/backend.py
jacinle/image/codecs.py
jacinle/image/imgio.py
jacinle/image/imgproc.py
jacinle/io/__init__.py
jacinle/io/common.py
jacinle/io/fs.py
jacinle/io/network.py
jacinle/io/pretty.py
jacinle/jit/__init__.py
jacinle/jit/cext/__init__.py
jacinle/jit/cext/travis.py
jacinle/jit/cython/__init__.py
jacinle/jit/cython/jit_compile.py
jacinle/nd/__init__.py
jacinle/nd/batch.py
jacinle/nd/indexing.py
jacinle/nd/meta.py
jacinle/nd/shape.py
jacinle/random/__init__.py
jacinle/random/_lazy_bind.py
jacinle/random/rng.py
jacinle/storage/__init__.py
jacinle/storage/unsafe_queue.py
jacinle/storage/kv/__init__.py
jacinle/storage/kv/base.py
jacinle/storage/kv/lmdb.py
jacinle/storage/kv/mem.py
jacinle/storage/kv/memcached.py
jacinle/utils/__init__.py
jacinle/utils/_inspect_mate.py
jacinle/utils/_termcolor.py
jacinle/utils/argument.py
jacinle/utils/cache.py
jacinle/utils/clipboard.py
jacinle/utils/container.py
jacinle/utils/context.py
jacinle/utils/debug.py
jacinle/utils/defaults.py
jacinle/utils/deprecated.py
jacinle/utils/enum.py
jacinle-1.0.4.dist-info/METADATA
jacinle-1.0.4.dist-info/WHEEL
jacinle-1.0.4.dist-info/licenses/LICENSE
jacinle-1.0.4.dist-info/RECORD
