Metadata-Version: 2.4
Name: jacinle
Version: 1.0.4
Summary: Jacinle
Project-URL: Homepage, https://github.com/vacancy/Jacinle
Project-URL: Issues, https://github.com/vacancy/Jacinle/issues
Author-email: Jiayuan Mao <maojiayuan@gmail.com>
License-Expression: MIT
License-File: LICENSE
Keywords: 
Classifier: License :: OSI Approved :: MIT License
Classifier: Operating System :: OS Independent
Classifier: Programming Language :: Python :: 3
Requires-Python: >=3.8
Requires-Dist: cython
Requires-Dist: ipdb
Requires-Dist: matplotlib
Requires-Dist: numpy
Requires-Dist: pkgconfig
Requires-Dist: pyyaml
Requires-Dist: pyzmq
Requires-Dist: scikit-learn
Requires-Dist: scipy
Requires-Dist: tabulate
Requires-Dist: tqdm
